Metadata-Version: 2.1
Name: pyinit2
Version: 1.1.0
Summary: Initialize blank python package
Home-page: https://github.com/benjiemc/pyinit2
Author: Benjamin McMaster
Author-email: benjamin.mcmaster@alumni.ubc.ca
License: MIT
Provides-Extra: develop
License-File: LICENSE
